weight_calc_interface/__init__.py
weight_calc_interface/models.py
weight_calc_interface-0.1.2.dist-info/METADATA
weight_calc_interface-0.1.2.dist-info/WHEEL
weight_calc_interface-0.1.2.dist-info/RECORD
