Metadata-Version: 2.1
Name: weight-calc-interface
Version: 0.1.2
Summary: Интерфейс для сервиса weight_calc.
Author: Alena Chegodaikina
Author-email: alena@promsoft.ru
Requires-Python: >=3.10,<4.0
Classifier: Programming Language :: Python :: 3
Classifier: Programming Language :: Python :: 3.10
Classifier: Programming Language :: Python :: 3.11
Requires-Dist: pydantic (>=1.10.7,<2.0.0)
